{
    "Subject": 11,
    "Trial": 3,
    "Code": "11-3",
    "Age": 65,
    "Gender": "F",
    "Height": 1.71,
    "Weight": 55,
    "BMI": 18.8,
    "Laterality": "Right",
    "Sensor": "TCon",
    "WalkedDistance": 10,
    "WalkingSpeed": 2.4,
    "PathologyGroup": "Neurological",
    "IsControl": "No",
    "LeftFootActivity": [
        [
            669,
            752
        ],
        [
            773,
            857
        ],
        [
            882,
            964
        ],
        [
            986,
            1068
        ],
        [
            1091,
            1169
        ],
        [
            1191,
            1280
        ],
        [
            1297,
            1381
        ],
        [
            1415,
            1477
        ],
        [
            1529,
            1614
        ],
        [
            1638,
            1716
        ],
        [
            1746,
            1823
        ],
        [
            1849,
            1927
        ],
        [
            1954,
            2033
        ],
        [
            2056,
            2136
        ],
        [
            2164,
            2244
        ],
        [
            2284,
            2366
        ]
    ],
    "RightFootActivity": [
        [
            619,
            690
        ],
        [
            725,
            809
        ],
        [
            833,
            914
        ],
        [
            937,
            1017
        ],
        [
            1040,
            1123
        ],
        [
            1145,
            1224
        ],
        [
            1248,
            1330
        ],
        [
            1359,
            1435
        ],
        [
            1477,
            1543
        ],
        [
            1600,
            1665
        ],
        [
            1693,
            1770
        ],
        [
            1799,
            1874
        ],
        [
            1902,
            1981
        ],
        [
            2005,
            2084
        ],
        [
            2112,
            2190
        ],
        [
            2222,
            2310
        ]
    ]
}