{
    "Subject": 134,
    "Trial": 6,
    "Code": "134-6",
    "Age": 67,
    "Gender": "M",
    "Height": 1.8,
    "Weight": 80,
    "BMI": 24.7,
    "Laterality": "Right",
    "Sensor": "TCon",
    "WalkedDistance": 10,
    "WalkingSpeed": 1.7,
    "PathologyGroup": "Neurological",
    "IsControl": "No",
    "LeftFootActivity": [
        [
            328,
            456
        ],
        [
            474,
            556
        ],
        [
            573,
            657
        ],
        [
            684,
            745
        ],
        [
            777,
            847
        ],
        [
            876,
            945
        ],
        [
            975,
            1045
        ],
        [
            1068,
            1134
        ],
        [
            1163,
            1229
        ],
        [
            1249,
            1325
        ],
        [
            1368,
            1429
        ],
        [
            1516,
            1590
        ],
        [
            1632,
            1703
        ],
        [
            1749,
            1805
        ],
        [
            1836,
            1914
        ],
        [
            1934,
            2008
        ],
        [
            2031,
            2102
        ],
        [
            2135,
            2201
        ],
        [
            2234,
            2303
        ],
        [
            2334,
            2402
        ],
        [
            2436,
            2515
        ],
        [
            2546,
            2623
        ]
    ],
    "RightFootActivity": [
        [
            308,
            384
        ],
        [
            426,
            506
        ],
        [
            525,
            603
        ],
        [
            625,
            704
        ],
        [
            733,
            801
        ],
        [
            827,
            895
        ],
        [
            916,
            991
        ],
        [
            1016,
            1084
        ],
        [
            1107,
            1178
        ],
        [
            1206,
            1289
        ],
        [
            1325,
            1385
        ],
        [
            1422,
            1487
        ],
        [
            1583,
            1647
        ],
        [
            1689,
            1765
        ],
        [
            1781,
            1861
        ],
        [
            1884,
            1960
        ],
        [
            1981,
            2056
        ],
        [
            2089,
            2158
        ],
        [
            2189,
            2250
        ],
        [
            2279,
            2353
        ],
        [
            2381,
            2462
        ],
        [
            2486,
            2564
        ],
        [
            2604,
            2682
        ]
    ]
}