{
    "Subject": 148,
    "Trial": 4,
    "Code": "148-4",
    "Age": 85,
    "Gender": "M",
    "Height": 1.57,
    "Weight": 55,
    "BMI": 22.3,
    "Laterality": "Right",
    "Sensor": "TCon",
    "WalkedDistance": 10,
    "WalkingSpeed": 1.9,
    "PathologyGroup": "Healthy",
    "IsControl": "Yes",
    "LeftFootActivity": [
        [
            55,
            157
        ],
        [
            188,
            302
        ],
        [
            325,
            415
        ],
        [
            432,
            523
        ],
        [
            555,
            627
        ],
        [
            648,
            745
        ],
        [
            774,
            860
        ],
        [
            888,
            983
        ],
        [
            1021,
            1103
        ],
        [
            1261,
            1329
        ],
        [
            1389,
            1440
        ],
        [
            1482,
            1559
        ],
        [
            1588,
            1684
        ],
        [
            1702,
            1804
        ],
        [
            1817,
            1911
        ],
        [
            1928,
            2004
        ],
        [
            2033,
            2117
        ],
        [
            2151,
            2250
        ],
        [
            2275,
            2371
        ]
    ],
    "RightFootActivity": [
        [
            151,
            224
        ],
        [
            253,
            354
        ],
        [
            374,
            462
        ],
        [
            489,
            581
        ],
        [
            606,
            687
        ],
        [
            717,
            804
        ],
        [
            835,
            930
        ],
        [
            951,
            1037
        ],
        [
            1057,
            1165
        ],
        [
            1178,
            1264
        ],
        [
            1285,
            1360
        ],
        [
            1410,
            1503
        ],
        [
            1530,
            1613
        ],
        [
            1640,
            1724
        ],
        [
            1766,
            1843
        ],
        [
            1888,
            1961
        ],
        [
            1979,
            2069
        ],
        [
            2083,
            2172
        ],
        [
            2206,
            2300
        ]
    ]
}