{
    "Subject": 162,
    "Trial": 5,
    "Code": "162-5",
    "Age": 50,
    "Gender": "F",
    "Height": 1.62,
    "Weight": 65,
    "BMI": 24.8,
    "Laterality": "Right",
    "Sensor": "TCon",
    "WalkedDistance": 10,
    "WalkingSpeed": 1.7,
    "PathologyGroup": "Neurological",
    "IsControl": "No",
    "LeftFootActivity": [
        [
            424,
            504
        ],
        [
            549,
            624
        ],
        [
            662,
            728
        ],
        [
            767,
            840
        ],
        [
            882,
            949
        ],
        [
            983,
            1054
        ],
        [
            1095,
            1164
        ],
        [
            1200,
            1275
        ],
        [
            1308,
            1379
        ],
        [
            1417,
            1491
        ],
        [
            1539,
            1592
        ],
        [
            1646,
            1724
        ],
        [
            1773,
            1844
        ],
        [
            1882,
            1948
        ],
        [
            1985,
            2058
        ],
        [
            2092,
            2159
        ],
        [
            2191,
            2257
        ],
        [
            2298,
            2360
        ],
        [
            2391,
            2475
        ],
        [
            2514,
            2586
        ],
        [
            2627,
            2710
        ]
    ],
    "RightFootActivity": [
        [
            368,
            443
        ],
        [
            483,
            575
        ],
        [
            602,
            678
        ],
        [
            711,
            786
        ],
        [
            827,
            902
        ],
        [
            933,
            1005
        ],
        [
            1041,
            1111
        ],
        [
            1144,
            1223
        ],
        [
            1253,
            1322
        ],
        [
            1359,
            1435
        ],
        [
            1477,
            1537
        ],
        [
            1593,
            1650
        ],
        [
            1715,
            1793
        ],
        [
            1836,
            1899
        ],
        [
            1931,
            2003
        ],
        [
            2038,
            2110
        ],
        [
            2151,
            2210
        ],
        [
            2244,
            2311
        ],
        [
            2342,
            2419
        ],
        [
            2453,
            2530
        ],
        [
            2572,
            2646
        ]
    ]
}