{
    "Subject": 172,
    "Trial": 4,
    "Code": "172-4",
    "Age": 53,
    "Gender": "M",
    "Height": 1.74,
    "Weight": 80,
    "BMI": 26.4,
    "Laterality": "Right",
    "Sensor": "XSens",
    "WalkedDistance": 10,
    "WalkingSpeed": 2.7,
    "PathologyGroup": "Healthy",
    "IsControl": "Yes",
    "LeftFootActivity": [
        [
            576,
            639
        ],
        [
            683,
            750
        ],
        [
            781,
            856
        ],
        [
            891,
            962
        ],
        [
            1000,
            1070
        ],
        [
            1106,
            1175
        ],
        [
            1218,
            1277
        ],
        [
            1319,
            1398
        ],
        [
            1448,
            1509
        ],
        [
            1551,
            1615
        ],
        [
            1655,
            1720
        ],
        [
            1766,
            1828
        ],
        [
            1881,
            1951
        ]
    ],
    "RightFootActivity": [
        [
            511,
            579
        ],
        [
            621,
            698
        ],
        [
            736,
            803
        ],
        [
            843,
            911
        ],
        [
            951,
            1014
        ],
        [
            1058,
            1124
        ],
        [
            1158,
            1226
        ],
        [
            1271,
            1342
        ],
        [
            1396,
            1451
        ],
        [
            1503,
            1561
        ],
        [
            1610,
            1667
        ],
        [
            1713,
            1773
        ],
        [
            1830,
            1892
        ],
        [
            1953,
            1994
        ]
    ]
}