{
    "Subject": 202,
    "Trial": 4,
    "Code": "202-4",
    "Age": 66,
    "Gender": "M",
    "Height": 1.68,
    "Weight": 92,
    "BMI": 32.6,
    "Laterality": "Right",
    "Sensor": "TCon",
    "WalkedDistance": 10,
    "WalkingSpeed": 1.2,
    "PathologyGroup": "Neurological",
    "IsControl": "No",
    "LeftFootActivity": [
        [
            441,
            560
        ],
        [
            577,
            700
        ],
        [
            721,
            828
        ],
        [
            853,
            958
        ],
        [
            980,
            1087
        ],
        [
            1108,
            1210
        ],
        [
            1222,
            1338
        ],
        [
            1361,
            1470
        ],
        [
            1492,
            1595
        ],
        [
            1621,
            1716
        ],
        [
            1737,
            1826
        ],
        [
            1870,
            1921
        ],
        [
            1989,
            2079
        ],
        [
            2141,
            2213
        ],
        [
            2262,
            2354
        ],
        [
            2386,
            2483
        ],
        [
            2514,
            2609
        ],
        [
            2643,
            2732
        ],
        [
            2761,
            2854
        ],
        [
            2885,
            2977
        ],
        [
            3005,
            3099
        ],
        [
            3122,
            3222
        ],
        [
            3251,
            3359
        ],
        [
            3380,
            3474
        ],
        [
            3506,
            3606
        ],
        [
            3634,
            3729
        ],
        [
            3757,
            3820
        ]
    ],
    "RightFootActivity": [
        [
            495,
            615
        ],
        [
            653,
            758
        ],
        [
            791,
            885
        ],
        [
            914,
            1017
        ],
        [
            1039,
            1140
        ],
        [
            1167,
            1260
        ],
        [
            1293,
            1395
        ],
        [
            1433,
            1533
        ],
        [
            1556,
            1660
        ],
        [
            1675,
            1769
        ],
        [
            1779,
            1868
        ],
        [
            1917,
            1974
        ],
        [
            2081,
            2141
        ],
        [
            2201,
            2291
        ],
        [
            2320,
            2414
        ],
        [
            2448,
            2540
        ],
        [
            2581,
            2671
        ],
        [
            2703,
            2797
        ],
        [
            2822,
            2915
        ],
        [
            2940,
            3040
        ],
        [
            3062,
            3159
        ],
        [
            3187,
            3280
        ],
        [
            3311,
            3402
        ],
        [
            3439,
            3537
        ],
        [
            3571,
            3669
        ],
        [
            3692,
            3789
        ]
    ]
}