{
    "Subject": 202,
    "Trial": 2,
    "Code": "202-2",
    "Age": 66,
    "Gender": "M",
    "Height": 1.68,
    "Weight": 92,
    "BMI": 32.6,
    "Laterality": "Right",
    "Sensor": "TCon",
    "WalkedDistance": 10,
    "WalkingSpeed": 1.2,
    "PathologyGroup": "Neurological",
    "IsControl": "No",
    "LeftFootActivity": [
        [
            296,
            410
        ],
        [
            453,
            546
        ],
        [
            577,
            674
        ],
        [
            705,
            796
        ],
        [
            818,
            917
        ],
        [
            938,
            1038
        ],
        [
            1067,
            1153
        ],
        [
            1178,
            1284
        ],
        [
            1301,
            1400
        ],
        [
            1422,
            1526
        ],
        [
            1543,
            1636
        ],
        [
            1658,
            1734
        ],
        [
            1793,
            1847
        ],
        [
            1927,
            1983
        ],
        [
            2019,
            2126
        ],
        [
            2144,
            2239
        ],
        [
            2273,
            2378
        ],
        [
            2397,
            2484
        ],
        [
            2526,
            2629
        ],
        [
            2648,
            2736
        ],
        [
            2765,
            2862
        ],
        [
            2890,
            2975
        ],
        [
            3003,
            3110
        ],
        [
            3136,
            3231
        ],
        [
            3264,
            3356
        ],
        [
            3391,
            3476
        ],
        [
            3516,
            3639
        ]
    ],
    "RightFootActivity": [
        [
            236,
            332
        ],
        [
            375,
            486
        ],
        [
            510,
            607
        ],
        [
            640,
            730
        ],
        [
            758,
            851
        ],
        [
            876,
            972
        ],
        [
            1002,
            1099
        ],
        [
            1127,
            1215
        ],
        [
            1243,
            1332
        ],
        [
            1360,
            1458
        ],
        [
            1480,
            1578
        ],
        [
            1600,
            1699
        ],
        [
            1712,
            1788
        ],
        [
            1849,
            1924
        ],
        [
            1987,
            2054
        ],
        [
            2082,
            2179
        ],
        [
            2204,
            2305
        ],
        [
            2327,
            2428
        ],
        [
            2460,
            2556
        ],
        [
            2591,
            2679
        ],
        [
            2704,
            2799
        ],
        [
            2830,
            2916
        ],
        [
            2944,
            3041
        ],
        [
            3070,
            3165
        ],
        [
            3198,
            3287
        ],
        [
            3316,
            3416
        ],
        [
            3450,
            3541
        ],
        [
            3561,
            3651
        ]
    ]
}