{
    "Subject": 35,
    "Trial": 1,
    "Code": "35-1",
    "Age": 83,
    "Gender": "M",
    "Height": 1.55,
    "Weight": 55,
    "BMI": 22.9,
    "Laterality": "Right",
    "Sensor": "TCon",
    "WalkedDistance": 10,
    "WalkingSpeed": 0.7,
    "PathologyGroup": "Neurological",
    "IsControl": "No",
    "LeftFootActivity": [
        [
            338,
            373
        ],
        [
            424,
            465
        ],
        [
            558,
            600
        ],
        [
            668,
            711
        ],
        [
            783,
            827
        ],
        [
            893,
            946
        ],
        [
            1015,
            1062
        ],
        [
            1124,
            1179
        ],
        [
            1234,
            1293
        ],
        [
            1354,
            1412
        ],
        [
            1480,
            1526
        ],
        [
            1596,
            1645
        ],
        [
            1704,
            1770
        ],
        [
            1827,
            1880
        ],
        [
            1943,
            2000
        ],
        [
            2060,
            2117
        ],
        [
            2174,
            2233
        ],
        [
            2288,
            2351
        ],
        [
            2410,
            2463
        ],
        [
            2524,
            2577
        ],
        [
            2639,
            2692
        ],
        [
            2750,
            2799
        ],
        [
            2867,
            2920
        ],
        [
            2979,
            3036
        ],
        [
            3097,
            3154
        ],
        [
            3212,
            3263
        ],
        [
            3322,
            3367
        ],
        [
            3405,
            3441
        ],
        [
            3477,
            3520
        ],
        [
            3574,
            3608
        ],
        [
            3663,
            3699
        ],
        [
            3974,
            4004
        ],
        [
            4075,
            4128
        ],
        [
            4196,
            4247
        ],
        [
            4315,
            4378
        ],
        [
            4437,
            4493
        ],
        [
            4554,
            4615
        ],
        [
            4673,
            4730
        ],
        [
            4799,
            4861
        ],
        [
            4924,
            4985
        ],
        [
            5047,
            5110
        ],
        [
            5164,
            5226
        ],
        [
            5288,
            5350
        ],
        [
            5408,
            5466
        ],
        [
            5523,
            5581
        ],
        [
            5640,
            5697
        ],
        [
            5751,
            5809
        ],
        [
            5868,
            5926
        ],
        [
            5983,
            6034
        ],
        [
            6090,
            6141
        ],
        [
            6201,
            6249
        ],
        [
            6305,
            6351
        ],
        [
            6399,
            6471
        ]
    ],
    "RightFootActivity": [
        [
            284,
            347
        ],
        [
            515,
            573
        ],
        [
            610,
            678
        ],
        [
            722,
            795
        ],
        [
            850,
            905
        ],
        [
            952,
            1025
        ],
        [
            1083,
            1138
        ],
        [
            1195,
            1249
        ],
        [
            1308,
            1366
        ],
        [
            1429,
            1492
        ],
        [
            1537,
            1607
        ],
        [
            1662,
            1722
        ],
        [
            1764,
            1841
        ],
        [
            1897,
            1957
        ],
        [
            2015,
            2071
        ],
        [
            2130,
            2185
        ],
        [
            2233,
            2298
        ],
        [
            2347,
            2417
        ],
        [
            2472,
            2535
        ],
        [
            2586,
            2650
        ],
        [
            2704,
            2761
        ],
        [
            2808,
            2879
        ],
        [
            2929,
            2991
        ],
        [
            3040,
            3110
        ],
        [
            3155,
            3225
        ],
        [
            3277,
            3332
        ],
        [
            3439,
            3471
        ],
        [
            3521,
            3593
        ],
        [
            3621,
            3674
        ],
        [
            3695,
            3731
        ],
        [
            3930,
            3987
        ],
        [
            4027,
            4083
        ],
        [
            4131,
            4211
        ],
        [
            4265,
            4326
        ],
        [
            4377,
            4450
        ],
        [
            4494,
            4569
        ],
        [
            4616,
            4685
        ],
        [
            4739,
            4813
        ],
        [
            4874,
            4939
        ],
        [
            4980,
            5062
        ],
        [
            5095,
            5180
        ],
        [
            5229,
            5301
        ],
        [
            5347,
            5420
        ],
        [
            5450,
            5534
        ],
        [
            5585,
            5651
        ],
        [
            5694,
            5765
        ],
        [
            5814,
            5882
        ],
        [
            5917,
            5996
        ],
        [
            6023,
            6104
        ],
        [
            6147,
            6216
        ]
    ]
}