{
    "Subject": 39,
    "Trial": 3,
    "Code": "39-3",
    "Age": 78,
    "Gender": "M",
    "Height": 1.6,
    "Weight": 72,
    "BMI": 28.1,
    "Laterality": "Right",
    "Sensor": "XSens",
    "WalkedDistance": 8.5,
    "WalkingSpeed": 1.0,
    "PathologyGroup": "Orthopedic",
    "IsControl": "No",
    "LeftFootActivity": [
        [
            625,
            713
        ],
        [
            790,
            871
        ],
        [
            946,
            1019
        ],
        [
            1093,
            1176
        ],
        [
            1250,
            1331
        ],
        [
            1411,
            1492
        ],
        [
            1571,
            1644
        ],
        [
            1720,
            1813
        ],
        [
            1889,
            1972
        ],
        [
            2048,
            2143
        ],
        [
            2269,
            2333
        ],
        [
            2402,
            2487
        ],
        [
            2542,
            2619
        ],
        [
            2700,
            2781
        ],
        [
            2857,
            2932
        ],
        [
            3021,
            3093
        ],
        [
            3177,
            3250
        ],
        [
            3323,
            3404
        ],
        [
            3489,
            3564
        ],
        [
            3640,
            3725
        ],
        [
            3802,
            3878
        ]
    ],
    "RightFootActivity": [
        [
            563,
            644
        ],
        [
            706,
            799
        ],
        [
            860,
            948
        ],
        [
            1003,
            1108
        ],
        [
            1162,
            1258
        ],
        [
            1322,
            1420
        ],
        [
            1479,
            1574
        ],
        [
            1631,
            1726
        ],
        [
            1795,
            1898
        ],
        [
            1959,
            2062
        ],
        [
            2185,
            2275
        ],
        [
            2330,
            2411
        ],
        [
            2468,
            2554
        ],
        [
            2623,
            2714
        ],
        [
            2775,
            2866
        ],
        [
            2931,
            3027
        ],
        [
            3098,
            3183
        ],
        [
            3244,
            3331
        ],
        [
            3403,
            3500
        ],
        [
            3552,
            3648
        ],
        [
            3709,
            3807
        ],
        [
            3876,
            3958
        ]
    ]
}