{
    "Subject": 43,
    "Trial": 4,
    "Code": "43-4",
    "Age": 35,
    "Gender": "M",
    "Height": 1.77,
    "Weight": 68,
    "BMI": 21.7,
    "Laterality": "Right",
    "Sensor": "XSens",
    "WalkedDistance": 10,
    "WalkingSpeed": 2.3,
    "PathologyGroup": "Healthy",
    "IsControl": "Yes",
    "LeftFootActivity": [
        [
            346,
            416
        ],
        [
            468,
            536
        ],
        [
            576,
            649
        ],
        [
            690,
            753
        ],
        [
            798,
            864
        ],
        [
            907,
            983
        ],
        [
            1025,
            1089
        ],
        [
            1147,
            1227
        ],
        [
            1310,
            1384
        ],
        [
            1426,
            1499
        ],
        [
            1544,
            1610
        ],
        [
            1652,
            1719
        ],
        [
            1764,
            1832
        ],
        [
            1879,
            1946
        ],
        [
            1994,
            2060
        ]
    ],
    "RightFootActivity": [
        [
            403,
            480
        ],
        [
            522,
            590
        ],
        [
            634,
            699
        ],
        [
            746,
            811
        ],
        [
            858,
            924
        ],
        [
            968,
            1041
        ],
        [
            1083,
            1147
        ],
        [
            1247,
            1321
        ],
        [
            1372,
            1439
        ],
        [
            1488,
            1553
        ],
        [
            1603,
            1669
        ],
        [
            1716,
            1777
        ],
        [
            1825,
            1890
        ],
        [
            1940,
            2008
        ]
    ]
}