{
    "Subject": 73,
    "Trial": 5,
    "Code": "73-5",
    "Age": 70,
    "Gender": "M",
    "Height": 1.81,
    "Weight": 81,
    "BMI": 24.7,
    "Laterality": "Right",
    "Sensor": "TCon",
    "WalkedDistance": 10,
    "WalkingSpeed": 2.3,
    "PathologyGroup": "Neurological",
    "IsControl": "No",
    "LeftFootActivity": [
        [
            340,
            419
        ],
        [
            455,
            533
        ],
        [
            572,
            639
        ],
        [
            676,
            749
        ],
        [
            777,
            846
        ],
        [
            871,
            955
        ],
        [
            988,
            1058
        ],
        [
            1093,
            1164
        ],
        [
            1263,
            1323
        ],
        [
            1370,
            1455
        ],
        [
            1481,
            1558
        ],
        [
            1582,
            1662
        ],
        [
            1685,
            1771
        ],
        [
            1810,
            1874
        ],
        [
            1910,
            1985
        ],
        [
            2014,
            2129
        ]
    ],
    "RightFootActivity": [
        [
            388,
            481
        ],
        [
            506,
            587
        ],
        [
            614,
            695
        ],
        [
            723,
            799
        ],
        [
            829,
            894
        ],
        [
            933,
            1008
        ],
        [
            1052,
            1112
        ],
        [
            1139,
            1217
        ],
        [
            1297,
            1392
        ],
        [
            1418,
            1505
        ],
        [
            1532,
            1615
        ],
        [
            1650,
            1718
        ],
        [
            1746,
            1815
        ],
        [
            1856,
            1931
        ],
        [
            1965,
            2047
        ]
    ]
}