{
    "Subject": 78,
    "Trial": 2,
    "Code": "78-2",
    "Age": 58,
    "Gender": "M",
    "Height": 1.82,
    "Weight": 87,
    "BMI": 26.3,
    "Laterality": "Right",
    "Sensor": "TCon",
    "WalkedDistance": 10,
    "WalkingSpeed": 1.0,
    "PathologyGroup": "Neurological",
    "IsControl": "No",
    "LeftFootActivity": [
        [
            296,
            351
        ],
        [
            435,
            495
        ],
        [
            569,
            631
        ],
        [
            710,
            777
        ],
        [
            851,
            910
        ],
        [
            976,
            1032
        ],
        [
            1104,
            1158
        ],
        [
            1229,
            1281
        ],
        [
            1353,
            1410
        ],
        [
            1479,
            1536
        ],
        [
            1611,
            1673
        ],
        [
            1745,
            1810
        ],
        [
            1883,
            1943
        ],
        [
            2016,
            2072
        ],
        [
            2147,
            2206
        ],
        [
            2283,
            2334
        ],
        [
            2430,
            2480
        ],
        [
            2585,
            2630
        ],
        [
            2712,
            2767
        ],
        [
            2841,
            2915
        ],
        [
            2986,
            3042
        ],
        [
            3123,
            3180
        ],
        [
            3243,
            3312
        ],
        [
            3391,
            3454
        ],
        [
            3530,
            3595
        ],
        [
            3673,
            3732
        ],
        [
            3804,
            3872
        ],
        [
            3944,
            3996
        ],
        [
            4061,
            4126
        ],
        [
            4206,
            4271
        ],
        [
            4346,
            4400
        ],
        [
            4487,
            4544
        ]
    ],
    "RightFootActivity": [
        [
            349,
            441
        ],
        [
            495,
            582
        ],
        [
            632,
            725
        ],
        [
            773,
            865
        ],
        [
            901,
            985
        ],
        [
            1029,
            1115
        ],
        [
            1160,
            1235
        ],
        [
            1281,
            1364
        ],
        [
            1410,
            1492
        ],
        [
            1531,
            1619
        ],
        [
            1666,
            1757
        ],
        [
            1804,
            1893
        ],
        [
            1941,
            2027
        ],
        [
            2069,
            2155
        ],
        [
            2210,
            2290
        ],
        [
            2368,
            2436
        ],
        [
            2498,
            2590
        ],
        [
            2645,
            2723
        ],
        [
            2780,
            2853
        ],
        [
            2921,
            2996
        ],
        [
            3064,
            3135
        ],
        [
            3189,
            3256
        ],
        [
            3319,
            3403
        ],
        [
            3482,
            3543
        ],
        [
            3603,
            3685
        ],
        [
            3743,
            3815
        ],
        [
            3881,
            3959
        ],
        [
            4007,
            4077
        ],
        [
            4138,
            4217
        ],
        [
            4281,
            4355
        ],
        [
            4416,
            4495
        ]
    ]
}